catplot/analysis.py
catplot/asimov.py
catplot/binning.py
catplot/cli.py
catplot/colour.py
catplot/io.py
catplot/latex.py
catplot/plotting.py
gw_catalog_plotter-0.0.2.dist-info/licenses/LICENSE
gw_catalog_plotter-0.0.2.dist-info/METADATA
gw_catalog_plotter-0.0.2.dist-info/WHEEL
gw_catalog_plotter-0.0.2.dist-info/entry_points.txt
gw_catalog_plotter-0.0.2.dist-info/top_level.txt
gw_catalog_plotter-0.0.2.dist-info/RECORD
